implicit_reca/__init__.py
implicit_reca/implicit_reca.py
implicit_reca-0.0.1.dist-info/LICENSE.txt
implicit_reca-0.0.1.dist-info/METADATA
implicit_reca-0.0.1.dist-info/WHEEL
implicit_reca-0.0.1.dist-info/top_level.txt
implicit_reca-0.0.1.dist-info/RECORD
