Metadata-Version: 2.1
Name: implicit-reca
Version: 0.0.1
Summary: Package for implicit recommendations
Home-page: https://github.com/BALaka-18/implicit_rec-official
Author: Balaka Biswas
Author-email: balaka2605@gmail.com
License: UNKNOWN
Platform: UNKNOWN
Classifier: Programming Language :: Python :: 3
Classifier: License :: OSI Approved :: MIT License
Classifier: Operating System :: OS Independent
Requires-Python: >=3.6
